Computer Organization and Architecture/Assembly Level Programs/32-Bit Register File/ques2.v
// 3 Port register file
//Shushant Kumar 16CO143
//Anmol Horo 16CO206

module regs(regno1,regno2,wreg,write,rdata1,rdata2,wdata,clk);
input [4:0] regno1;            // read register 1
input [4:0] regno2;            // read register 2
input [4:0] wreg;              // write register
input write;                   // write signal
output reg [31:0] rdata1;      // read data 1
output reg [31:0] rdata2;      // read data 2
input [31:0] wdata;            // write data
input clk;                     // clock
reg [31:0] r0;                 // registers 0 to 31
reg [31:0] r1;      
reg [31:0] r2;               
reg [31:0] r3;
reg [31:0] r4;
reg [31:0] r5;
reg [31:0] r6;
reg [31:0] r7;
reg [31:0] r8;
reg [31:0] r9;
reg [31:0] r10;
reg [31:0] r11;
reg [31:0] r12;
reg [31:0] r13;
reg [31:0] r14;
reg [31:0] r15;
reg [31:0] r16;
reg [31:0] r17;
reg [31:0] r18;
reg [31:0] r19;
reg [31:0] r20;
reg [31:0] r21;
reg [31:0] r22;
reg [31:0] r23;
reg [31:0] r24;
reg [31:0] r25;
reg [31:0] r26;
reg [31:0] r27;
reg [31:0] r28;
reg [31:0] r29;
reg [31:0] r30;
reg [31:0] r31;

always @ (posedge clk)     // works only at the positive edge of the clock 
begin
begin           
		   // according to regno1 , the rdata1 is assigned the value of that particular register
if( regno1 == 0)   
rdata1=r0;
else if( regno1==1)
rdata1=r1;
else if( regno1==2)
rdata1=r2;
else if( regno1==3)
rdata1=r3;
else if( regno1==4)
rdata1=r4;
else if( regno1==5)
rdata1=r5;
else if( regno1==6)
rdata1=r6;
else if( regno1==7)
rdata1=r7;
else if( regno1==8)
rdata1=r8;
else if( regno1==9)
rdata1=r9;
else if( regno1==10)
rdata1=r10;
else if( regno1==11)
rdata1=r11;
else if( regno1==12)
rdata1=r12;
else if( regno1==13)
rdata1=r13;
else if( regno1==14)
rdata1=r14;
else if( regno1==15)
rdata1=r15;
else if( regno1==16)
rdata1=r16;
else if( regno1==17)
rdata1=r17;
else if( regno1==18)
rdata1=r18;
else if( regno1==19)
rdata1=r19;
else if( regno1==20)
rdata1=r20;
else if( regno1==21)
rdata1=r21;
else if( regno1==22)
rdata1=r22;
else if( regno1==23)
rdata1=r23;
else if( regno1==24)
rdata1=r24;
else if( regno1==25)
rdata1=r25;
else if( regno1==26)
rdata1=r26;
else if( regno1==27)
rdata1=r27;
else if( regno1==28)
rdata1=r28;
else if( regno1==29)
rdata1=r29;
else if( regno1==30)
rdata1=r30;
else if( regno1==31)
rdata1=r31;
end

begin
                         // according to regno2 , the rdata2 is assigned the value of that particular register
if( regno2 == 0)
rdata2=r0;
else if( regno2==1)
rdata2=r1;
else if( regno2==2)
rdata2=r2;
else if( regno2==3)
rdata2=r3;
else if( regno2==4)
rdata2=r4;
else if( regno2==5)
rdata2=r5;
else if( regno2==6)
rdata2=r6;
else if( regno2==7)
rdata2=r7;
else if( regno2==8)
rdata2=r8;
else if( regno2==9)
rdata2=r9;
else if( regno2==10)
rdata2=r10;
else if( regno2==11)
rdata2=r11;
else if( regno2==12)
rdata2=r12;
else if( regno2==13)
rdata2=r13;
else if( regno2==14)
rdata2=r14;
else if( regno2==15)
rdata2=r15;
else if( regno2==16)
rdata2=r16;
else if( regno2==17)
rdata2=r17;
else if( regno2==18)
rdata2=r18;
else if( regno2==19)
rdata2=r19;
else if( regno2==20)
rdata2=r20;
else if( regno2==21)
rdata2=r21;
else if( regno2==22)
rdata2=r22;
else if( regno2==23)
rdata2=r23;
else if( regno2==24)
rdata2=r24;
else if( regno2==25)
rdata2=r25;
else if( regno2==26)
rdata2=r26;
else if( regno2==27)
rdata2=r27;
else if( regno2==28)
rdata2=r28;
else if( regno2==29)
rdata2=r29;
else if( regno2==30)
rdata2=r30;
else if( regno2==31)
rdata2=r31;
end

if(write==1)               // when write signal is 1 then only values are written on to the register
begin
                           // according to wreg , the value of wdata is stored in that particular register
if( wreg == 0)
r0=wdata;
else if( wreg==1)
r1=wdata;
else if( wreg==2)
r2=wdata;
else if( wreg==3)
r3=wdata;
else if( wreg==4)
r4=wdata;
else if( wreg==5)
r5=wdata;
else if( wreg==6)
r6=wdata;
else if( wreg==7)
r7=wdata;
else if( wreg==8)
r8=wdata;
else if( wreg==9)
r9=wdata;
else if( wreg==10)
r10=wdata;
else if( wreg==11)
r11=wdata;
else if( wreg==12)
r12=wdata;
else if( wreg==13)
r13=wdata;
else if( wreg==14)
r14=wdata;
else if( wreg==15)
r15=wdata;
else if( wreg==16)
r16=wdata;
else if( wreg==17)
r17=wdata;
else if( wreg==18)
r18=wdata;
else if( wreg==19)
r19=wdata;
else if( wreg==20)
r20=wdata;
else if( wreg==21)
r21=wdata;
else if( wreg==22)
r22=wdata;
else if( wreg==23)
r23=wdata;
else if( wreg==24)
r24=wdata;
else if( wreg==25)
r25=wdata;
else if( wreg==26)
r26=wdata;
else if( wreg==27)
r27=wdata;
else if( wreg==28)
r28=wdata;
else if( wreg==29)
r29=wdata;
else if( wreg==30)
r30=wdata;
else if( wreg==31)
r31=wdata;
end
end
endmodule

Computer Organization and Architecture/Assembly Level Programs/32-Bit Register File/tques2.v
// Testbench for 3 Port register file
//Shushant Kumar 16CO143
//Anmol Horo 16CO206


`timescale 1ns/10ps

module t_reg;
	
	reg [4:0] regno1;           // read register 1
    reg [4:0] regno2;           // read register 2
    reg [4:0] wreg;             // write register
    reg write;                  // write signal
    wire [31:0] rdata1;         // read data 1
    wire [31:0] rdata2;         // read data 2
    reg [31:0] wdata;           // write data
	reg clk;                    // clock	
	regs s(regno1,regno2,wreg,write,rdata1,rdata2,wdata,clk);
	initial begin
       
	$dumpfile("ques2gtk.vcd");        // GTK file generated
    $dumpvars(0, t_reg);          
	
	 
	  
	regno1=5'b00000;             // reading from this register number
	regno2=5'b00100;             // reading from this register number
	write=1'b1;                  // when write signal is 1 then only data is written on to the register
	wreg=5'b00000;               // writing to this register number
	wdata=32'b00001011;          // writhing this data
	
	
	#10                           // variation of inputs
	regno1=5'b00000;
	regno2=5'b00110;
	write=1'b1;
	wreg=5'b01000;
	wdata=8'b00001111;
	
	#10
	regno1=5'b01000;
	regno2=5'b00000;
	write=1'b1;
	wreg=5'b00110;
	wdata=2'b11;
	
	#10
	regno1=5'b00110;
	regno2=5'b01000;
	write=1'b1;
	wreg=5'b00010;
	wdata=32'b101011;
	
	#10
	regno1=5'b00110;
	regno2=5'b00010;
	wreg=5'b01001;
	wdata=8'b11000001;
	
	#10
	regno1=5'b01001;
	regno2=5'b01000;
	wreg=5'b01010;
	wdata=4'b1111;
	
	#10
	regno1=5'b00110;
	regno2=5'b00000;
	wreg=5'b01011;
	wdata=32'b11110001;
	
	#10
	regno1=5'b01011;
	regno2=5'b01011;
	wreg=5'b01100;
	wdata=32'b10101010101;
	
	#10
	regno1=5'b01100;
	regno2=5'b01000;
	wreg=5'b11000;
	wdata=32'b1111000001101;
	
	#10
	regno1=5'b11000;
	regno2=5'b00010;
	wreg=5'b11100;
	wdata=32'b110101110001101;
	
	#10
	regno1=5'b11100;
	regno2=5'b11000;
	wreg=5'b11110;
	wdata=32'b10101010001111;
	
	#10
	regno1=5'b11110;
	regno2=5'b11000;
	wreg=5'b11111;
	wdata=32'b11001000111000;
	
	#10
	regno1=5'b00010;
	regno2=5'b11111;
	wreg=5'b00001;
	wdata=32'b11001101;
	
	#10
	regno1=5'b00001;
	regno2=5'b00010;
	wreg=5'b00011;
	wdata=32'b01111110111;
	
	#10
	regno1=5'b00111;
	regno2=5'b00011;
	wreg=5'b00111;
	wdata=32'b110010111110;
	
	#10
	regno1=5'b01001;
	regno2=5'b00111;
	write=1'b0;
	
	#10
	regno1=5'b01100;
	regno2=5'b00001;
	write=1'b1;
	wreg=5'b00100;
	wdata=32'b101000011101;
	
	#10
	regno1=5'b11000;
	regno2=5'b11110;
	write=1'b0;
	
	#10
	regno1=5'b00011;
	regno2=5'b11111;
	write=1'b1;
	wreg=5'b01111;
	wdata=32'b10000111000101;
	
	#10
	regno1=5'b01111;
	regno2=5'b01011;
	write=1'b1;
	wreg=5'b10001;
	wdata=32'b10101111;
	
	#10
	regno1=5'b01010;
	regno2=5'b00110;
	write=1'b1;
	wreg=5'b01000;
	wdata=32'b0101011011;
	
	#10
	regno1=5'b01000;
	regno2=5'b11000;
	write=1'b0;
	
	#10
	regno1=5'b00011;
	regno2=5'b00111;
	write=1'b1;
	wreg=5'b10101;
	wdata=32'b10101101011;
	
	#10
	regno1=5'b10101;
	regno2=5'b10001;
	write=1'b1;
	wreg=5'b01110;
	wdata=32'b11110101011;
	
	end 
	
		initial
		begin
		clk = 1'b0;     // value for clock
		repeat (56)
		#5 clk = ~clk;
		end
	 initial #280 $finish;
	 
	 initial begin
	   // display
       $monitor("read reg1:%b   read reg2:%b   data1:%b  data2:%b  write:%b    write reg:%b   write data:%b \n",regno1,regno2,rdata1,rdata2,write,wreg,wdata);
       end	
endmodule

Computer Organization and Architecture/Assembly Level Programs/32-Bit Register File/ques2gtk.vcd
$date
	Mon Oct 30 23:55:28 2017
$end
$version
	Icarus Verilog
$end
$timescale
	10ps
$end
$scope module t_reg $end
$var wire 32 ! rdata2 [31:0] $end
$var wire 32 " rdata1 [31:0] $end
$var reg 1 # clk $end
$var reg 5 $ regno1 [4:0] $end
$var reg 5 % regno2 [4:0] $end
$var reg 32 & wdata [31:0] $end
$var reg 5 ' wreg [4:0] $end
$var reg 1 ( write $end
$scope module s $end
$var wire 1 # clk $end
$var wire 5 ) regno1 [4:0] $end
$var wire 5 * regno2 [4:0] $end
$var wire 32 + wdata [31:0] $end
$var wire 5 , wreg [4:0] $end
$var wire 1 ( write $end
$var reg 32 - r0 [31:0] $end
$var reg 32 . r1 [31:0] $end
$var reg 32 / r10 [31:0] $end
$var reg 32 0 r11 [31:0] $end
$var reg 32 1 r12 [31:0] $end
$var reg 32 2 r13 [31:0] $end
$var reg 32 3 r14 [31:0] $end
$var reg 32 4 r15 [31:0] $end
$var reg 32 5 r16 [31:0] $end
$var reg 32 6 r17 [31:0] $end
$var reg 32 7 r18 [31:0] $end
$var reg 32 8 r19 [31:0] $end
$var reg 32 9 r2 [31:0] $end
$var reg 32 : r20 [31:0] $end
$var reg 32 ; r21 [31:0] $end
$var reg 32 < r22 [31:0] $end
$var reg 32 = r23 [31:0] $end
$var reg 32 > r24 [31:0] $end
$var reg 32 ? r25 [31:0] $end
$var reg 32 @ r26 [31:0] $end
$var reg 32 A r27 [31:0] $end
$var reg 32 B r28 [31:0] $end
$var reg 32 C r29 [31:0] $end
$var reg 32 D r3 [31:0] $end
$var reg 32 E r30 [31:0] $end
$var reg 32 F r31 [31:0] $end
$var reg 32 G r4 [31:0] $end
$var reg 32 H r5 [31:0] $end
$var reg 32 I r6 [31:0] $end
$var reg 32 J r7 [31:0] $end
$var reg 32 K r8 [31:0] $end
$var reg 32 L r9 [31:0] $end
$var reg 32 M rdata1 [31:0] $end
$var reg 32 N rdata2 [31:0] $end
$upscope $end
$upscope $end
$enddefinitions $end
#0
$dumpvars
bx N
bx M
bx L
bx K
bx J
bx I
bx H
bx G
bx F
bx E
bx D
bx C
bx B
bx A
bx @
bx ?
bx >
bx =
bx <
bx ;
bx :
bx 9
bx 8
bx 7
bx 6
bx 5
bx 4
bx 3
bx 2
bx 1
bx 0
bx /
bx .
bx -
b0 ,
b1011 +
b100 *
b0 )
1(
b0 '
b1011 &
b100 %
b0 $
0#
bx "
bx !
$end
#500
b1011 -
1#
#1000
0#
b1111 &
b1111 +
b1000 '
b1000 ,
b110 %
b110 *
#1500
b1111 K
b1011 "
b1011 M
1#
#2000
0#
b11 &
b11 +
b110 '
b110 ,
b0 %
b0 *
b1000 $
b1000 )
#2500
b11 I
b1011 !
b1011 N
b1111 "
b1111 M
1#
#3000
0#
b101011 &
b101011 +
b10 '
b10 ,
b1000 %
b1000 *
b110 $
b110 )
#3500
b101011 9
b1111 !
b1111 N
b11 "
b11 M
1#
#4000
0#
b11000001 &
b11000001 +
b1001 '
b1001 ,
b10 %
b10 *
#4500
b11000001 L
b101011 !
b101011 N
1#
#5000
0#
b1111 &
b1111 +
b1010 '
b1010 ,
b1000 %
b1000 *
b1001 $
b1001 )
#5500
b1111 /
b1111 !
b1111 N
b11000001 "
b11000001 M
1#
#6000
0#
b11110001 &
b11110001 +
b1011 '
b1011 ,
b0 %
b0 *
b110 $
b110 )
#6500
b11110001 0
b1011 !
b1011 N
b11 "
b11 M
1#
#7000
0#
b10101010101 &
b10101010101 +
b1100 '
b1100 ,
b1011 %
b1011 *
b1011 $
b1011 )
#7500
b10101010101 1
b11110001 !
b11110001 N
b11110001 "
b11110001 M
1#
#8000
0#
b1111000001101 &
b1111000001101 +
b11000 '
b11000 ,
b1000 %
b1000 *
b1100 $
b1100 )
#8500
b1111000001101 >
b1111 !
b1111 N
b10101010101 "
b10101010101 M
1#
#9000
0#
b110101110001101 &
b110101110001101 +
b11100 '
b11100 ,
b10 %
b10 *
b11000 $
b11000 )
#9500
b110101110001101 B
b101011 !
b101011 N
b1111000001101 "
b1111000001101 M
1#
#10000
0#
b10101010001111 &
b10101010001111 +
b11110 '
b11110 ,
b11000 %
b11000 *
b11100 $
b11100 )
#10500
b10101010001111 E
b1111000001101 !
b1111000001101 N
b110101110001101 "
b110101110001101 M
1#
#11000
0#
b11001000111000 &
b11001000111000 +
b11111 '
b11111 ,
b11110 $
b11110 )
#11500
b11001000111000 F
b10101010001111 "
b10101010001111 M
1#
#12000
0#
b11001101 &
b11001101 +
b1 '
b1 ,
b11111 %
b11111 *
b10 $
b10 )
#12500
b11001101 .
b11001000111000 !
b11001000111000 N
b101011 "
b101011 M
1#
#13000
0#
b1111110111 &
b1111110111 +
b11 '
b11 ,
b10 %
b10 *
b1 $
b1 )
#13500
b1111110111 D
b101011 !
b101011 N
b11001101 "
b11001101 M
1#
#14000
0#
b110010111110 &
b110010111110 +
b111 '
b111 ,
b11 %
b11 *
b111 $
b111 )
#14500
b110010111110 J
b1111110111 !
b1111110111 N
bx "
bx M
1#
#15000
0#
0(
b111 %
b111 *
b1001 $
b1001 )
#15500
b110010111110 !
b110010111110 N
b11000001 "
b11000001 M
1#
#16000
0#
b101000011101 &
b101000011101 +
b100 '
b100 ,
1(
b1 %
b1 *
b1100 $
b1100 )
#16500
b101000011101 G
b11001101 !
b11001101 N
b10101010101 "
b10101010101 M
1#
#17000
0#
0(
b11110 %
b11110 *
b11000 $
b11000 )
#17500
b10101010001111 !
b10101010001111 N
b1111000001101 "
b1111000001101 M
1#
#18000
0#
b10000111000101 &
b10000111000101 +
b1111 '
b1111 ,
1(
b11111 %
b11111 *
b11 $
b11 )
#18500
b10000111000101 4
b11001000111000 !
b11001000111000 N
b1111110111 "
b1111110111 M
1#
#19000
0#
b10101111 &
b10101111 +
b10001 '
b10001 ,
b1011 %
b1011 *
b1111 $
b1111 )
#19500
b10101111 6
b11110001 !
b11110001 N
b10000111000101 "
b10000111000101 M
1#
#20000
0#
b101011011 &
b101011011 +
b1000 '
b1000 ,
b110 %
b110 *
b1010 $
b1010 )
#20500
b101011011 K
b11 !
b11 N
b1111 "
b1111 M
1#
#21000
0#
0(
b11000 %
b11000 *
b1000 $
b1000 )
#21500
b1111000001101 !
b1111000001101 N
b101011011 "
b101011011 M
1#
#22000
0#
b10101101011 &
b10101101011 +
b10101 '
b10101 ,
1(
b111 %
b111 *
b11 $
b11 )
#22500
b10101101011 ;
b110010111110 !
b110010111110 N
b1111110111 "
b1111110111 M
1#
#23000
0#
b11110101011 &
b11110101011 +
b1110 '
b1110 ,
b10001 %
b10001 *
b10101 $
b10101 )
#23500
b11110101011 3
b10101111 !
b10101111 N
b10101101011 "
b10101101011 M
1#
