Computer Organization and Architecture/Assembly Level Programs/1-Bit ALU/ques1.v
//1 Bit ALU Main File
//Shushant Kumar 16CO143
//Anmol Horo 16CO206


module alu(a,b,ainvert,binvert,carryin,op,result,cout,z,flag2);
input a,b,ainvert,binvert,carryin;                                  //Inputs 
input [1:0] op;                                                     //Inputs
output reg result,cout,z;	                                          //Outputs
output flag2;                                                       //Output flag2

wire a1,b1;
assign a1 = (a & ~ainvert) | (~a & ainvert);                        //When ainvert=0 => a1=a and ainvert=1 => a1=~a
assign b1=(b & ~binvert) | (~b & binvert);                          //When binvert=0 => b1=b and binvert=1 => b1=~b
assign flag2= a&(~b);                                               //Calculating Flag2 which is true only for a=1,b=0
  
  always @ (*)
  begin
    if(op==0)                                                       //AND or NOR operation of a and b depending on value of 
    result=a1&b1;                                                   //ainvert and binvert
    else if(op==1)                                                  //NAND or OR operation of a and b depending on value of 
      result=a1|b1;                                                 //ainvert and binvert
    else if(op==2)
      begin
        result = a1^b1^carryin;                                     //ADDITION or SUBTRACTION depending on carryin
        cout = ( ((a1 ^ b1) & carryin) | ( a1 & b1 )  );
      end
    if(result == 0)
      z=1;                                                           //setting flag1 'z' depending on result
    else
      z=0;
  end
  
 endmodule

Computer Organization and Architecture/Assembly Level Programs/1-Bit ALU/tques1.v
//1 Bit ALU Testbench
//Shushant Kumar 16CO143
//Anmol Horo 16CO206

`timescale 1ns/10ps

module t_alu;					
	
	reg a,b,ainvert,binvert,carryin;			//Inputs 
	reg [1:0] op;								//Inputs
	wire result,cout,z,flag2;					//Outputs
	
	alu s(a,b,ainvert,binvert,carryin,op,result,cout,z,flag2);		//Module Instantiation
 
	initial begin

	$dumpfile("ques1gtk.vcd");					//GTK File generated
        $dumpvars(0, t_alu);
         ainvert=1'b0;							//setting ainvert to 0
	     binvert=1'b0;							//setting binvert to 0
		 carryin=1'b0;							//setting carryin to 0
		 op=2'b00;
	  
         a=1'b0;								//Signal for AND
		 b=1'b0;
	#10 
        a = 1'b0; 
        b = 1'b1; 
        
	#10
        a = 1'b1; 
        b = 1'b0; 
        
	#10
        a = 1'b1; 
        b = 1'b1; 
		
	#10 
	     ainvert=1'b0;							//Signal for OR
	     binvert=1'b0;
		 carryin=1'b0;
		 op=2'b01;
	  
         a=1'b0;
		 b=1'b0;
	 #10 
        a = 1'b0; 
        b = 1'b1; 
        
	#10
        a = 1'b1; 
        b = 1'b0; 
        
	#10
        a = 1'b1; 
        b = 1'b1; 
    	
	#10 
	     ainvert=1'b1;							//Signal for NOR
	     binvert=1'b1;
		 carryin=1'b1;
		 op=2'b00;
	  
         a=1'b0;
		 b=1'b0;
	 #10 
        a = 1'b0; 
        b = 1'b1; 
        
	#10
        a = 1'b1; 
        b = 1'b0; 
        
	#10
        a = 1'b1; 
        b = 1'b1; 
		
	#10 
	     ainvert=1'b1;							//Signal for NAND					
	     binvert=1'b1;
		 carryin=1'b0;
		 op=2'b01;
	  
         a=1'b0;
		 b=1'b0;
	 #10 
        a = 1'b0; 
        b = 1'b1; 
        
	#10
        a = 1'b1; 
        b = 1'b0; 
        
	#10
        a = 1'b1; 
        b = 1'b1; 	
		
	#10 
	     ainvert=1'b0;							//Signal for SUBTRACTION
	     binvert=1'b1;
		 carryin=1'b1;
		 op=2'b10;
	  
         a=1'b0;
		 b=1'b0;
	 #10 
        a = 1'b0; 
        b = 1'b1; 
        
	#10
        a = 1'b1; 
        b = 1'b0; 
        
	#10
        a = 1'b1; 
        b = 1'b1; 	
		
	#10 
	     ainvert=1'b0;							//Signal for ADDITION
	     binvert=1'b0;
		 carryin=1'b0;
		 op=2'b10;
	  
         a=1'b0;
		 b=1'b0;
	 #10 
        a = 1'b0; 
        b = 1'b1; 
        
	#10
        a = 1'b1; 
        b = 1'b0; 
        
	#10
        a = 1'b1; 
        b = 1'b1; 	
	
    end  
	 initial #240 $finish;
	
       initial begin		
       $monitor("a=%b, b=%b, ainvert=%b , binvert=%b , carryin=%b , op =%b , result = %b , cout = %b , z =%b , flag2= %b\n",a,b,ainvert,binvert,carryin,op,result,cout,z,flag2);
       end	
endmodule

Computer Organization and Architecture/Assembly Level Programs/1-Bit ALU/ques1gtk.vcd
$date
	Mon Oct 30 23:19:42 2017
$end
$version
	Icarus Verilog
$end
$timescale
	10ps
$end
$scope module t_alu $end
$var wire 1 ! z $end
$var wire 1 " result $end
$var wire 1 # flag2 $end
$var wire 1 $ cout $end
$var reg 1 % a $end
$var reg 1 & ainvert $end
$var reg 1 ' b $end
$var reg 1 ( binvert $end
$var reg 1 ) carryin $end
$var reg 2 * op [1:0] $end
$scope module s $end
$var wire 1 % a $end
$var wire 1 + a1 $end
$var wire 1 & ainvert $end
$var wire 1 ' b $end
$var wire 1 , b1 $end
$var wire 1 ( binvert $end
$var wire 1 ) carryin $end
$var wire 1 # flag2 $end
$var wire 2 - op [1:0] $end
$var reg 1 $ cout $end
$var reg 1 " result $end
$var reg 1 ! z $end
$upscope $end
$upscope $end
$enddefinitions $end
#0
$dumpvars
b0 -
0,
0+
b0 *
0)
0(
0'
0&
0%
x$
0#
0"
1!
$end
#1000
1,
1'
#2000
0,
1#
1+
0'
1%
#3000
0!
1"
1,
0#
1'
#4000
1!
0"
0,
0+
0'
0%
b1 *
b1 -
#5000
0!
1"
1,
1'
#6000
0,
1#
1+
0'
1%
#7000
1,
0#
1'
#8000
0'
0%
b0 *
b0 -
1)
1(
1&
#9000
1!
0"
0,
1'
#10000
1,
0+
1#
0'
1%
#11000
0,
0#
1'
#12000
0!
1"
1,
1+
0'
0%
b1 *
b1 -
0)
#13000
0,
1'
#14000
1,
0+
1#
0'
1%
#15000
1!
0"
0,
0#
1'
#16000
1,
1!
1$
0"
0'
0%
b10 *
b10 -
1)
0&
#17000
0!
0$
1"
0,
1'
#18000
1,
0!
1$
1"
1#
1+
0'
1%
#19000
1!
0"
0,
0#
1'
#20000
0+
1!
0$
0"
0'
0%
0)
0(
#21000
0!
1"
1,
1'
#22000
0,
1#
1+
0'
1%
#23000
1!
1$
0"
1,
0#
1'
